mms_client/__init__.py
mms_client/client.py
mms_client/py.typed
mms_client/schemas/wsdl/mi-web-service-jbms.wsdl
mms_client/schemas/wsdl/omi-web-service.wsdl
mms_client/schemas/xsd/mi-market.xsd
mms_client/schemas/xsd/mi-outbnd-reports.xsd
mms_client/schemas/xsd/mi-report.xsd
mms_client/schemas/xsd/mpr.xsd
mms_client/schemas/xsd/omi.xsd
mms_client/security/__init__.py
mms_client/security/certs.py
mms_client/security/crypto.py
mms_client/services/__init__.py
mms_client/services/base.py
mms_client/services/market.py
mms_client/services/omi.py
mms_client/services/registration.py
mms_client/services/report.py
mms_client/types/__init__.py
mms_client/types/award.py
mms_client/types/base.py
mms_client/types/bup.py
mms_client/types/enums.py
mms_client/types/fields.py
mms_client/types/market.py
mms_client/types/offer.py
mms_client/types/omi.py
mms_client/types/registration.py
mms_client/types/report.py
mms_client/types/reserve.py
mms_client/types/resource.py
mms_client/types/settlement.py
mms_client/types/surplus_capcity.py
mms_client/types/transport.py
mms_client/utils/__init__.py
mms_client/utils/errors.py
mms_client/utils/multipart_transport.py
mms_client/utils/plugin.py
mms_client/utils/serialization.py
mms_client/utils/web.py
mms_client-1.11.1.dist-info/LICENSE
mms_client-1.11.1.dist-info/METADATA
mms_client-1.11.1.dist-info/WHEEL
mms_client-1.11.1.dist-info/RECORD
