Metadata-Version: 2.1
Name: mms-client
Version: 1.11.1
Summary: API client for accessing the MMS
Home-page: https://github.com/ElectroRoute-Japan/mms-client
Author: Ryan Wood
Author-email: ryan.wood@electroroute.co.jp
Requires-Python: >=3.12,<4.0
Classifier: Development Status :: 5 - Production/Stable
Classifier: Framework :: Pydantic :: 2
Classifier: Framework :: Pytest
Classifier: Intended Audience :: Developers
Classifier: License :: OSI Approved :: The Unlicense (Unlicense)
Classifier: Natural Language :: English
Classifier: Operating System :: OS Independent
Classifier: Programming Language :: Python :: 3
Classifier: Programming Language :: Python :: 3 :: Only
Classifier: Programming Language :: Python :: 3.12
Classifier: Topic :: Software Development :: Libraries :: Python Modules
Classifier: Typing :: Typed
Requires-Dist: backoff (>=2.2.1,<3.0.0)
Requires-Dist: cryptography (>=42.0.5,<43.0.0)
Requires-Dist: lxml (>=5.1.0,<6.0.0)
Requires-Dist: pendulum (>=3.0.0,<4.0.0)
Requires-Dist: pycryptodomex (>=3.20.0,<4.0.0)
Requires-Dist: pydantic (>=2.6.3,<3.0.0)
Requires-Dist: pydantic-extra-types (>=2.7.0,<3.0.0)
Requires-Dist: pydantic-xml (>=2.9.0,<3.0.0)
Requires-Dist: requests (>=2.31.0,<3.0.0)
Requires-Dist: requests-pkcs12 (>=1.24,<2.0)
Requires-Dist: xmlschema (>=3.0.2,<4.0.0)
Requires-Dist: zeep (>=4.2.1,<5.0.0)
